<?xml version="1.0" encoding="UTF-8"?>
<eveapi version="2">
  <currentTime>2013-07-08 12:06:13</currentTime>
  <result>
    <rowset name="contractList" key="contractID" columns="contractID,issuerID,issuerCorpID,assigneeID,acceptorID,startStationID,endStationID,type,status,title,forCorp,availability,dateIssued,dateExpired,dateAccepted,numDays,dateCompleted,price,reward,collateral,buyout,volume">
      <row contractID="69929209" issuerID="91227546" issuerCorpID="98012536" assigneeID="0" acceptorID="0" startStationID="60011866" endStationID="60011866" type="ItemExchange" status="Outstanding" title="Perfect or near-perfect ME" forCorp="0" availability="Public" dateIssued="2013-07-02 16:53:02" dateExpired="2013-07-16 16:53:02" dateAccepted="" numDays="0" dateCompleted="" price="45000000.00" reward="0.00" collateral="0.00" buyout="0.00" volume="100" />
      <row contractID="69929288" issuerID="91227546" issuerCorpID="98012536" assigneeID="0" acceptorID="0" startStationID="60011866" endStationID="60011866" type="ItemExchange" status="Outstanding" title="Perfect or near-perfect ME" forCorp="0" availability="Public" dateIssued="2013-07-02 16:55:14" dateExpired="2013-07-16 16:55:14" dateAccepted="" numDays="0" dateCompleted="" price="60000000.00" reward="0.00" collateral="0.00" buyout="0.00" volume="100" />
      <row contractID="68984782" issuerID="91227546" issuerCorpID="98012536" assigneeID="0" acceptorID="93386857" startStationID="60011866" endStationID="60011866" type="ItemExchange" status="Completed" title="" forCorp="0" availability="Public" dateIssued="2013-06-09 15:43:42" dateExpired="2013-06-23 15:43:42" dateAccepted="2013-06-15 03:10:06" numDays="0" dateCompleted="2013-06-15 03:10:06" price="40000000.00" reward="0.00" collateral="0.00" buyout="0.00" volume="100" />
      <row contractID="69053796" issuerID="91227546" issuerCorpID="98012536" assigneeID="0" acceptorID="93219802" startStationID="60003760" endStationID="60011866" type="Courier" status="Completed" title="" forCorp="1" availability="Public" dateIssued="2013-06-11 00:26:38" dateExpired="2013-06-25 00:26:38" dateAccepted="2013-06-11 07:23:57" numDays="1" dateCompleted="2013-06-11 08:41:27" price="0.00" reward="2000000.00" collateral="1000000000.00" buyout="0.00" volume="49873.8" />
      <row contractID="69058056" issuerID="91227546" issuerCorpID="98012536" assigneeID="0" acceptorID="90689475" startStationID="60011866" endStationID="60011866" type="ItemExchange" status="Completed" title="Perfect or near-perfect ME" forCorp="0" availability="Public" dateIssued="2013-06-11 03:06:06" dateExpired="2013-06-25 03:06:06" dateAccepted="2013-06-16 18:49:07" numDays="0" dateCompleted="2013-06-16 18:49:07" price="60000000.00" reward="0.00" collateral="0.00" buyout="0.00" volume="100" />
      <row contractID="69300363" issuerID="91227546" issuerCorpID="98012536" assigneeID="0" acceptorID="93358107" startStationID="60011866" endStationID="60011866" type="ItemExchange" status="Completed" title="Perfect or near-perfect ME" forCorp="0" availability="Public" dateIssued="2013-06-16 20:05:57" dateExpired="2013-06-30 20:05:57" dateAccepted="2013-06-17 21:53:31" numDays="0" dateCompleted="2013-06-17 21:53:31" price="40000000.00" reward="0.00" collateral="0.00" buyout="0.00" volume="100" />
      <row contractID="69300424" issuerID="91227546" issuerCorpID="98012536" assigneeID="0" acceptorID="552088578" startStationID="60011866" endStationID="60011866" type="ItemExchange" status="Completed" title="Perfect or near-perfect ME" forCorp="0" availability="Public" dateIssued="2013-06-16 20:07:15" dateExpired="2013-06-30 20:07:15" dateAccepted="2013-06-18 02:20:59" numDays="0" dateCompleted="2013-06-18 02:20:59" price="60000000.00" reward="0.00" collateral="0.00" buyout="0.00" volume="100" />
      <row contractID="69371348" issuerID="91227546" issuerCorpID="98012536" assigneeID="0" acceptorID="1253235482" startStationID="60003760" endStationID="60011866" type="Courier" status="Completed" title="" forCorp="1" availability="Public" dateIssued="2013-06-18 15:52:56" dateExpired="2013-07-02 15:52:56" dateAccepted="2013-06-18 22:40:06" numDays="1" dateCompleted="2013-06-18 23:59:27" price="0.00" reward="1500000.00" collateral="600000000.00" buyout="0.00" volume="5025" />
      <row contractID="69410819" issuerID="91227546" issuerCorpID="98012536" assigneeID="0" acceptorID="1387050188" startStationID="60011866" endStationID="60011866" type="ItemExchange" status="Completed" title="Perfect or near-perfect ME" forCorp="0" availability="Public" dateIssued="2013-06-19 15:52:59" dateExpired="2013-07-03 15:52:59" dateAccepted="2013-06-25 22:54:42" numDays="0" dateCompleted="2013-06-25 22:54:42" price="60000000.00" reward="0.00" collateral="0.00" buyout="0.00" volume="100" />
      <row contractID="69410849" issuerID="91227546" issuerCorpID="98012536" assigneeID="0" acceptorID="1172345842" startStationID="60011866" endStationID="60011866" type="ItemExchange" status="Completed" title="Perfect or near-perfect ME" forCorp="0" availability="Public" dateIssued="2013-06-19 15:54:01" dateExpired="2013-07-03 15:54:01" dateAccepted="2013-06-28 18:14:39" numDays="0" dateCompleted="2013-06-28 18:14:39" price="60000000.00" reward="0.00" collateral="0.00" buyout="0.00" volume="100" />
      <row contractID="69410898" issuerID="91227546" issuerCorpID="98012536" assigneeID="0" acceptorID="93352348" startStationID="60011866" endStationID="60011866" type="ItemExchange" status="Completed" title="Perfect or near-perfect ME" forCorp="0" availability="Public" dateIssued="2013-06-19 15:55:11" dateExpired="2013-07-03 15:55:11" dateAccepted="2013-06-20 14:09:10" numDays="0" dateCompleted="2013-06-20 14:09:10" price="40000000.00" reward="0.00" collateral="0.00" buyout="0.00" volume="100" />
      <row contractID="69464969" issuerID="91227546" issuerCorpID="98012536" assigneeID="0" acceptorID="93352348" startStationID="60011866" endStationID="60011866" type="ItemExchange" status="Completed" title="Perfect or near-perfect ME" forCorp="0" availability="Public" dateIssued="2013-06-20 23:30:15" dateExpired="2013-07-04 23:30:15" dateAccepted="2013-06-22 01:41:05" numDays="0" dateCompleted="2013-06-22 01:41:05" price="40000000.00" reward="0.00" collateral="0.00" buyout="0.00" volume="100" />
      <row contractID="69593251" issuerID="91227546" issuerCorpID="98012536" assigneeID="0" acceptorID="1497532851" startStationID="60011866" endStationID="60011866" type="ItemExchange" status="Completed" title="Perfect or near-perfect ME" forCorp="0" availability="Public" dateIssued="2013-06-23 23:54:29" dateExpired="2013-07-07 23:54:29" dateAccepted="2013-06-28 17:23:22" numDays="0" dateCompleted="2013-06-28 17:23:22" price="45000000.00" reward="0.00" collateral="0.00" buyout="0.00" volume="100" />
      <row contractID="69308327" issuerID="90192277" issuerCorpID="98190867" assigneeID="91227546" acceptorID="98012536" startStationID="60008494" endStationID="60008494" type="ItemExchange" status="Completed" title="" forCorp="0" availability="Private" dateIssued="2013-06-16 23:32:54" dateExpired="2013-06-30 23:32:54" dateAccepted="2013-06-19 15:49:25" numDays="0" dateCompleted="2013-06-19 15:49:25" price="80000000.00" reward="0.00" collateral="0.00" buyout="0.00" volume="22603.5" />
      <row contractID="69426275" issuerID="1523688185" issuerCorpID="98190867" assigneeID="91227546" acceptorID="91227546" startStationID="60012667" endStationID="60012667" type="ItemExchange" status="Completed" title="" forCorp="0" availability="Private" dateIssued="2013-06-19 23:14:20" dateExpired="2013-07-03 23:14:20" dateAccepted="2013-06-20 12:11:19" numDays="0" dateCompleted="2013-06-20 12:11:19" price="0.00" reward="0.00" collateral="0.00" buyout="0.00" volume="250000" />
      <row contractID="69812203" issuerID="90192277" issuerCorpID="98190867" assigneeID="91227546" acceptorID="98012536" startStationID="60008494" endStationID="60008494" type="ItemExchange" status="Completed" title="" forCorp="0" availability="Private" dateIssued="2013-06-29 17:14:15" dateExpired="2013-07-13 17:14:15" dateAccepted="2013-06-29 17:30:49" numDays="0" dateCompleted="2013-06-29 17:30:49" price="80000000.00" reward="0.00" collateral="0.00" buyout="0.00" volume="38433.12" />
      <row contractID="69946978" issuerID="90192277" issuerCorpID="98190867" assigneeID="91227546" acceptorID="98012536" startStationID="60010924" endStationID="60010924" type="ItemExchange" status="Completed" title="" forCorp="0" availability="Private" dateIssued="2013-07-03 02:02:08" dateExpired="2013-07-17 02:02:08" dateAccepted="2013-07-03 02:23:44" numDays="0" dateCompleted="2013-07-03 02:23:44" price="55000000.00" reward="0.00" collateral="0.00" buyout="0.00" volume="508" />
      <row contractID="69956588" issuerID="90192277" issuerCorpID="98190867" assigneeID="91227546" acceptorID="98012536" startStationID="60011866" endStationID="60011866" type="ItemExchange" status="Completed" title="" forCorp="0" availability="Private" dateIssued="2013-07-03 09:44:35" dateExpired="2013-07-17 09:44:35" dateAccepted="2013-07-03 09:56:50" numDays="0" dateCompleted="2013-07-03 09:56:50" price="95000000.00" reward="0.00" collateral="0.00" buyout="0.00" volume="19600" />
      <row contractID="70020196" issuerID="90192277" issuerCorpID="98190867" assigneeID="91227546" acceptorID="98012536" startStationID="60011866" endStationID="60011866" type="ItemExchange" status="Completed" title="" forCorp="0" availability="Private" dateIssued="2013-07-05 02:06:33" dateExpired="2013-07-19 02:06:33" dateAccepted="2013-07-05 12:11:24" numDays="0" dateCompleted="2013-07-05 12:11:24" price="12500000.00" reward="0.00" collateral="0.00" buyout="0.00" volume="18832.8" />
      <row contractID="69077760" issuerID="91541933" issuerCorpID="98012536" assigneeID="98012536" acceptorID="91227546" startStationID="60003295" endStationID="60011566" type="Courier" status="Completed" title="" forCorp="1" availability="Private" dateIssued="2013-06-11 16:00:55" dateExpired="2013-06-25 16:00:55" dateAccepted="2013-06-16 19:56:28" numDays="1" dateCompleted="2013-06-16 21:04:06" price="0.00" reward="0.00" collateral="0.00" buyout="0.00" volume="1000" />
      <row contractID="69446518" issuerID="92736777" issuerCorpID="98012536" assigneeID="98012536" acceptorID="91227546" startStationID="60011566" endStationID="60011866" type="Courier" status="Completed" title="" forCorp="1" availability="Private" dateIssued="2013-06-20 14:48:47" dateExpired="2013-07-04 14:48:47" dateAccepted="2013-06-20 14:49:10" numDays="1" dateCompleted="2013-06-20 15:02:57" price="0.00" reward="0.00" collateral="0.00" buyout="0.00" volume="1100" />
    </rowset>
  </result>
  <cachedUntil>2013-07-08 12:20:13</cachedUntil>
</eveapi>